adafruit_bd3491fs.py
adafruit_circuitpython_bd3491fs-1.1.22.dist-info/licenses/LICENSE
adafruit_circuitpython_bd3491fs-1.1.22.dist-info/METADATA
adafruit_circuitpython_bd3491fs-1.1.22.dist-info/WHEEL
adafruit_circuitpython_bd3491fs-1.1.22.dist-info/top_level.txt
adafruit_circuitpython_bd3491fs-1.1.22.dist-info/RECORD
